commands/__init__.py
commands/analyze.py
commands/config.py
commands/create.py
commands/doc.py
commands/lint.py
commands/security.py
templates/__init__.py
utils/__init__.py
utils/db.py
utils/file.py
utils/logger.py
backgen-0.1.dist-info/METADATA
backgen-0.1.dist-info/WHEEL
backgen-0.1.dist-info/entry_points.txt
backgen-0.1.dist-info/top_level.txt
backgen-0.1.dist-info/RECORD
