Metadata-Version: 2.4
Name: backgen
Version: 0.1
Summary: Générateur de structure de projet backend
Home-page: https://github.com/Jeck0v/Backend-generator
Author: Jeck0v
Author-email: sixen.siteweb@gmail.com
Classifier: Programming Language :: Python :: 3
Classifier: License :: OSI Approved :: MIT License
Classifier: Operating System :: OS Independent
Requires-Python: >=3.9
Requires-Dist: click
Requires-Dist: fastapi
Requires-Dist: pytest
Dynamic: requires-dist
